{
  "subtitle": "", 
  "description": "10. How else is the Ministry of Health protecting the Kenyan public?", 
  "language": "eng_UK", 
  "title": "10. How else is the Ministry of Health protecting the Kenyan public?", 
  "primary_category": "3f7de85fded64143abad90b9afbd0dec", 
  "created_at": "2014-11-07T12:45:51.657171+00:00", 
  "featured_in_category": true, 
  "modified_at": "2014-11-07T12:45:51.657361+00:00", 
  "_version": {
    "package_version": "0.2.6", 
    "language_version": "2.7.6", 
    "language_version_string": "2.7.6 (default, Mar 22 2014, 22:59:56) \n[GCC 4.8.2]", 
    "language": "python", 
    "package": "elastic-git"
  }, 
  "linked_pages": [], 
  "id": null, 
  "content": " - The Ministry of Health in collaboration with partners like WHO and KEMRI has established procedures in place to ensure the safe transport and care of patients with Ebola disease.\r\n - The Ministry also has procured special protective clothing for health workers and other people who may handle potentially infected persons.\r\n - Drugs and other medical supplies are also being prepositioned in strategic regions of the Country.", 
  "source": null, 
  "featured": false, 
  "published": null, 
  "position": 0, 
  "slug": "10-how-else-ministry-health-protecting-kenyan-public", 
  "uuid": "d62a60d490b94dd2bae9fba95fff76b8"
}